AthenaTwitchBot/__init__.py
AthenaTwitchBot/data/__init__.py
AthenaTwitchBot/data/global_vars.py
AthenaTwitchBot/data/irc_twitch.py
AthenaTwitchBot/data/message_flags.py
AthenaTwitchBot/data/output_types.py
AthenaTwitchBot/data/twitch_api_scopes.py
AthenaTwitchBot/data/twitch_api_urls.py
AthenaTwitchBot/functions/__init__.py
AthenaTwitchBot/functions/output_twitch_prep.py
AthenaTwitchBot/models/__init__.py
AthenaTwitchBot/models/launcher.py
AthenaTwitchBot/models/twitch_channel.py
AthenaTwitchBot/models/twitch_user.py
AthenaTwitchBot/models/twitch_api/__init__.py
AthenaTwitchBot/models/twitch_api/twitch_api.py
AthenaTwitchBot/models/twitch_api/twitch_api_user.py
AthenaTwitchBot/models/twitch_bot/__init__.py
AthenaTwitchBot/models/twitch_bot/bot_server.py
AthenaTwitchBot/models/twitch_bot/line_handler.py
AthenaTwitchBot/models/twitch_bot/logic_output.py
AthenaTwitchBot/models/twitch_bot/message_context.py
AthenaTwitchBot/models/twitch_bot/message_tags.py
AthenaTwitchBot/models/twitch_bot/twitch_bot.py
AthenaTwitchBot/models/twitch_bot/twitch_bot_protocol.py
AthenaTwitchBot/models/twitch_bot/bot_methods/__init__.py
AthenaTwitchBot/models/twitch_bot/bot_methods/bot_chat_message.py
AthenaTwitchBot/models/twitch_bot/bot_methods/bot_command.py
AthenaTwitchBot/models/twitch_bot/bot_methods/bot_custom_reward.py
AthenaTwitchBot/models/twitch_bot/bot_methods/bot_first_time_chatter.py
AthenaTwitchBot/models/twitch_bot/bot_methods/bot_mentioned.py
AthenaTwitchBot/models/twitch_bot/bot_methods/bot_mentioned_start.py
AthenaTwitchBot/models/twitch_bot/bot_methods/bot_task.py
AthenaTwitchBot/models/twitch_bot/bot_methods/bot_method_inheritance/__init__.py
AthenaTwitchBot/models/twitch_bot/bot_methods/bot_method_inheritance/callback.py
AthenaTwitchBot/models/twitch_bot/bot_methods/bot_method_inheritance/rate_limit.py
AthenaTwitchBot/models/twitch_bot/outputs/__init__.py
AthenaTwitchBot/models/twitch_bot/outputs/output.py
AthenaTwitchBot/models/twitch_bot/outputs/output_console.py
AthenaTwitchBot-0.8.1.dist-info/LICENSE
AthenaTwitchBot-0.8.1.dist-info/METADATA
AthenaTwitchBot-0.8.1.dist-info/WHEEL
AthenaTwitchBot-0.8.1.dist-info/top_level.txt
AthenaTwitchBot-0.8.1.dist-info/RECORD
